setup.cfg
setup.py
PyOnfido.egg-info/PKG-INFO
PyOnfido.egg-info/SOURCES.txt
PyOnfido.egg-info/dependency_links.txt
PyOnfido.egg-info/requires.txt
PyOnfido.egg-info/top_level.txt
onfido/__init__.py
onfido/addresspicker.py
onfido/api_resource.py
onfido/applicants.py
onfido/checks.py
onfido/defaults.py
onfido/documents.py
onfido/live_photos.py
onfido/onfido.py
onfido/reports.py
onfido/requestor.py
onfido/test/__init__.py
onfido/test/test_data.py
onfido/test/test_import.py
onfido/test/test_integration.py
onfido/test/test_requestor.py
onfido/test/test_resources.py