Metadata-Version: 1.1
Name: PyOnfido
Version: 0.5
Summary: Python wrapper library for Onfido's REST API for background checking.
Home-page: https://github.com/onfido/pyonfido
Author: Onfido
Author-email: engineering@onfido.com
License: BSD
Download-URL: https://github.com/onfido/pyonfido/tarball/0.5
Keywords: pyonfido onfido background
Platform: UNKNOWN
Classifier: Development Status :: 5 - Production/Stable 
Classifier: Intended Audience :: Developers
Classifier: License :: OSI Approved :: MIT License
Classifier: Topic :: Software Development :: Libraries
Classifier: Programming Language :: Python :: 2.6
Classifier: Programming Language :: Python :: 2.7
Classifier: Programming Language :: Python :: 3.0
Classifier: Programming Language :: Python :: 3.1
Classifier: Programming Language :: Python :: 3.2
Classifier: Programming Language :: Python :: 3.3
Classifier: Programming Language :: Python :: 3.4
Classifier: Programming Language :: Python :: 3.5
